doubleblind/__init__.py
doubleblind/blinding.py
doubleblind/editing.py
doubleblind/favicon.icns
doubleblind/favicon.ico
doubleblind/gui.py
doubleblind/gui_style.py
doubleblind/main.py
doubleblind/parametric_style.qss
doubleblind/splash.png
doubleblind/splash_transparent.png
doubleblind/utils.py
doubleblind-1.1.1.dist-info/LICENSE
doubleblind-1.1.1.dist-info/METADATA
doubleblind-1.1.1.dist-info/WHEEL
doubleblind-1.1.1.dist-info/entry_points.txt
doubleblind-1.1.1.dist-info/top_level.txt
doubleblind-1.1.1.dist-info/RECORD
