Metadata-Version: 2.1
Name: doubleblind
Version: 1.1.1
Summary: Automatically and reversibly replace file names with random strings to help experimenters quantify microscopy experiments blindly and maintain experimental integrity.
Author-email: Guy Teichman <guyteichman@gmail.com>
Maintainer-email: Guy Teichman <guyteichman@gmail.com>
License: MIT License
Project-URL: Homepage, https://github.com/guyteichman/DoubleBlind
Project-URL: Bug Reports, https://github.com/guyteichman/DoubleBlind/issues
Keywords: microscopy,blinding,double-blind,experiment,rename
Classifier: Development Status :: 5 - Production/Stable
Classifier: Intended Audience :: Developers
Classifier: Topic :: Software Development :: Build Tools
Classifier: License :: OSI Approved :: MIT License
Classifier: Programming Language :: Python :: 3
Classifier: Programming Language :: Python :: 3.8
Classifier: Programming Language :: Python :: 3.9
Classifier: Programming Language :: Python :: 3.10
Classifier: Programming Language :: Python :: 3.11
Classifier: Programming Language :: Python :: 3 :: Only
Requires-Python: >=3.8
License-File: LICENSE
Requires-Dist: PyQt6
Requires-Dist: cryptography
Requires-Dist: smaz-py3
Requires-Dist: openpyxl
Requires-Dist: qdarkstyle
Requires-Dist: requests
